discord_ext_commands_coghelper/__init__.py
discord_ext_commands_coghelper/coghelper.py
discord_ext_commands_coghelper/errors.py
discord_ext_commands_coghelper/utils/__init__.py
discord_ext_commands_coghelper/utils/contant.py
discord_ext_commands_coghelper/utils/dict.py
discord_ext_commands_coghelper/utils/discord.py
discord_ext_commands_coghelper/utils/misc.py
tests/__init__.py
tests/test_utils_dict.py
tests/test_utils_discord.py
tests/test_utils_misc.py
discord_ext_commands_coghelper-0.0.6.dist-info/METADATA
discord_ext_commands_coghelper-0.0.6.dist-info/WHEEL
discord_ext_commands_coghelper-0.0.6.dist-info/top_level.txt
discord_ext_commands_coghelper-0.0.6.dist-info/RECORD
